bigquant-0.1.0.dist-info/METADATA
bigquant-0.1.0.dist-info/WHEEL
bigquant-0.1.0.dist-info/licenses/LICENSE
bigquant/__init__.py
bigquant-0.1.0.dist-info/RECORD
